musix-0.1.1.dist-info/METADATA
musix-0.1.1.dist-info/LICENSE.md
musix-0.1.1.dist-info/LICENSE
musix-0.1.1.dist-info/top_level.txt
musix-0.1.1.dist-info/RECORD
musix-0.1.1.dist-info/WHEEL
musix/__init__.pyi
musix/__init__.py
musix/py.typed
musix/_musix.cpython-37m-x86_64-linux-gnu.so
musix/setup.py
musix/include/zconf.h
musix/include/zlib.h
musix/share/pkgconfig/zlib.pc
musix/share/man/man3/zlib.3
musix/lib/libz.a
musix/_musix/__init__.pyi
musix/data/STIL.txt
musix/data/hebios.bin
musix/data/Songlengths.md5
musix/data/example.lua
musix/data/adplug.db
musix/data/sc68/sc68.cfg
musix/data/sc68/Replay/lastninjaiii.bin
musix/data/sc68/Replay/ninjatfmx.bin
musix/data/sc68/Replay/stos.bin
musix/data/sc68/Replay/puma.bin
musix/data/sc68/Replay/quartet.bin.benbak
musix/data/sc68/Replay/megatizer.bin
musix/data/sc68/Replay/sndh_ice.bin
musix/data/sc68/Replay/psg1.bin
musix/data/sc68/Replay/jamcrackerpro.bin
musix/data/sc68/Replay/spacegun.bin
musix/data/sc68/Replay/soundfx.bin
musix/data/sc68/Replay/puma2.bin
musix/data/sc68/Replay/bendaglish.deli
musix/data/sc68/Replay/sidmon1.bin
musix/data/sc68/Replay/mcoder.bin
musix/data/sc68/Replay/mon_old.deli.bin
musix/data/sc68/Replay/huntforredoct.bin
musix/data/sc68/Replay/huelsbeck.bin
musix/data/sc68/Replay/mon.bin
musix/data/sc68/Replay/chipmon2.bin
musix/data/sc68/Replay/zonewarrior.bin
musix/data/sc68/Replay/synthiv.bin
musix/data/sc68/Replay/aenigmatica.bin
musix/data/sc68/Replay/fred.bin
musix/data/sc68/Replay/tao_ms25.bin
musix/data/sc68/Replay/tao_digi.bin
musix/data/sc68/Replay/hippel-coso_note.deli
musix/data/sc68/Replay/mon_old.deli
musix/data/sc68/Replay/metrocross.bin
musix/data/sc68/Replay/robhubbard.deli.bin
musix/data/sc68/Replay/bendaglish.deli.bin
musix/data/sc68/Replay/bs22.bin
musix/data/sc68/Replay/blipblop.bin
musix/data/sc68/Replay/nobuddiesland.bin
musix/data/sc68/Replay/sidmon2.bin
musix/data/sc68/Replay/fireice.bin
musix/data/sc68/Replay/test.bin
musix/data/sc68/Replay/mmme.bin
musix/data/sc68/Replay/ivanhoe.bin
musix/data/sc68/Replay/ssd1.bin
musix/data/sc68/Replay/hpn-jam.bin
musix/data/sc68/Replay/blipp079.bin
