Metadata-Version: 2.1
Name: musix
Version: 0.1.1
Summary: Music library
Author-email: Jonas Minnberg <sasq64@gmail.com>
License: Copyright 2022 Jonas Minnberg
Project-URL: repository, https://github.com/sasq64/musicplayer
Requires-Python: >=3.7
License-File: LICENSE
License-File: LICENSE.md
